convection/secrets/objects/keymapdb.py
convection/secrets/objects/nacl.py
convection/secrets/objects/authdb/group.py
convection/secrets/objects/authdb/token.py
convection/secrets/objects/authdb/user.py
convection/secrets/server/__init__.py
convection/secrets/server/convection-secrets.service
convection/secrets/server/core.py
convection/secrets/server/manager.py
convection/secrets/server/nacl.py
convection/secrets/server/setup.py
convection/secrets/server/uacl.py
convection/secrets/server/authdb/__init__.py
convection/secrets/server/authdb/acl.py
convection/secrets/server/authdb/auth.py
convection/secrets/server/authdb/core.py
convection/secrets/server/authdb/group.py
convection/secrets/server/authdb/user.py
convection/secrets/server/mgrcmd/__init__.py
convection/secrets/server/mgrcmd/auth.py
convection/secrets/server/mgrcmd/core.py
convection/secrets/server/mgrcmd/keys.py
convection/secrets/server/mgrcmd/secrets.py
convection/secrets/server/mgrcmd/store.py
convection/secrets/server/specs/nacl.item.spec
convection/secrets/server/specs/nacl.root.spec
convection/secrets/server/specs/plugin.secret.spec
convection/secrets/server/specs/secrets-controller.spec
convection/secrets/server/specs/secrets.manager.authentication.spec
convection/secrets/server/specs/secrets.manager.spec
convection/secrets/server/specs/service.config.spec
convection/secrets/server/specs/service.network.spec
convection/secrets/server/specs/service.spec
convection/secrets/server/specs/service.websocket.spec
convection/secrets/server/srvcmd/__init__.py
convection/secrets/server/srvcmd/acl.py
convection/secrets/server/srvcmd/core.py
convection/secrets/server/srvcmd/group.py
convection/secrets/server/srvcmd/keys.py
convection/secrets/server/srvcmd/secrets.py
convection/secrets/server/srvcmd/store.py
convection/secrets/server/srvcmd/user.py
convection_secrets_manager-1.0.1.dist-info/LICENSE.md
convection_secrets_manager-1.0.1.dist-info/METADATA
convection_secrets_manager-1.0.1.dist-info/WHEEL
convection_secrets_manager-1.0.1.dist-info/entry_points.txt
convection_secrets_manager-1.0.1.dist-info/top_level.txt
convection_secrets_manager-1.0.1.dist-info/RECORD
